bempp_cl/__init__.py
bempp_cl/helpers.py
bempp_cl/version.py
bempp_cl/api/__init__.py
bempp_cl/api/assembly/__init__.py
bempp_cl/api/assembly/assembler.py
bempp_cl/api/assembly/blocked_operator.py
bempp_cl/api/assembly/boundary_operator.py
bempp_cl/api/assembly/discrete_boundary_operator.py
bempp_cl/api/assembly/grid_function.py
bempp_cl/api/assembly/potential_operator.py
bempp_cl/api/external/__init__.py
bempp_cl/api/external/fenics.py
bempp_cl/api/external/fenicsx.py
bempp_cl/api/external/viewers.py
bempp_cl/api/fmm/__init__.py
bempp_cl/api/fmm/exafmm.py
bempp_cl/api/fmm/fmm_assembler.py
bempp_cl/api/fmm/helpers.py
bempp_cl/api/grid/__init__.py
bempp_cl/api/grid/grid.py
bempp_cl/api/grid/io.py
bempp_cl/api/integration/__init__.py
bempp_cl/api/integration/duffy_collocation.py
bempp_cl/api/integration/duffy_galerkin.py
bempp_cl/api/integration/gauss.py
bempp_cl/api/integration/triangle_gauss.py
bempp_cl/api/linalg/__init__.py
bempp_cl/api/linalg/direct_solvers.py
bempp_cl/api/linalg/iterative_solvers.py
bempp_cl/api/operators/__init__.py
bempp_cl/api/operators/boundary/__init__.py
bempp_cl/api/operators/boundary/common.py
bempp_cl/api/operators/boundary/helmholtz.py
bempp_cl/api/operators/boundary/laplace.py
bempp_cl/api/operators/boundary/maxwell.py
bempp_cl/api/operators/boundary/modified_helmholtz.py
bempp_cl/api/operators/boundary/sparse.py
bempp_cl/api/operators/far_field/__init__.py
bempp_cl/api/operators/far_field/helmholtz.py
bempp_cl/api/operators/far_field/maxwell.py
bempp_cl/api/operators/potential/__init__.py
bempp_cl/api/operators/potential/helmholtz.py
bempp_cl/api/operators/potential/laplace.py
bempp_cl/api/operators/potential/maxwell.py
bempp_cl/api/operators/potential/modified_helmholtz.py
bempp_cl/api/shapes/__init__.py
bempp_cl/api/shapes/regular_spheres.npz
bempp_cl/api/shapes/shapes.py
bempp_cl/api/space/__init__.py
bempp_cl/api/space/maxwell_spaces.py
bempp_cl/api/space/scalar_dual_spaces.py
bempp_cl/api/space/scalar_spaces.py
electroacpy-2025.7.1.dist-info/METADATA
electroacpy-2025.7.1.dist-info/WHEEL
electroacpy-2025.7.1.dist-info/licenses/LICENSE
electroacpy-2025.7.1.dist-info/RECORD
