Metadata-Version: 2.4
Name: electroacPy
Version: 2025.7.1
Summary: Package for electro-acoustics with LEM/BEM approach.
Author-email: Tom Munoz <munozt@outlook.fr>
License-File: LICENSE
Classifier: Operating System :: OS Independent
Classifier: Programming Language :: Python :: 3
Requires-Python: >=3.9
Requires-Dist: gmsh
Requires-Dist: matplotlib
Requires-Dist: meshio
Requires-Dist: numba
Requires-Dist: numpy
Requires-Dist: pandas
Requires-Dist: plotly
Requires-Dist: pyarrow
Requires-Dist: pyuff
Requires-Dist: pyvista
Requires-Dist: scipy
Requires-Dist: siphash24
Requires-Dist: tqdm
